charachorder/__init__.py
charachorder/__main__.py
charachorder/_types.py
charachorder/device.py
charachorder/errors.py
charachorder/py.typed
charachorder/types.py
charachorder-0.6.0.dist-info/METADATA
charachorder-0.6.0.dist-info/WHEEL
charachorder-0.6.0.dist-info/top_level.txt
charachorder-0.6.0.dist-info/RECORD
